xgt/AdminService_pb2.py
xgt/AdminService_pb2_grpc.py
xgt/DataService_pb2.py
xgt/DataService_pb2_grpc.py
xgt/ErrorMessages_pb2.py
xgt/GraphTypesService_pb2.py
xgt/GraphTypesService_pb2_grpc.py
xgt/JobService_pb2.py
xgt/JobService_pb2_grpc.py
xgt/MetricsService_pb2.py
xgt/MetricsService_pb2_grpc.py
xgt/SchemaMessages_pb2.py
xgt/__init__.py
xgt/common.py
xgt/connection.py
xgt/graph.py
xgt/job.py
xgt/version.py
xgt/admin/__init__.py
xgt-2.4.0.post1.dist-info/licenses/LICENSE.txt
xgt-2.4.0.post1.dist-info/METADATA
xgt-2.4.0.post1.dist-info/WHEEL
xgt-2.4.0.post1.dist-info/top_level.txt
xgt-2.4.0.post1.dist-info/RECORD
