Metadata-Version: 2.4
Name: xgt
Version: 2.4.0.post1
Summary: The Python interface to the Rocketgraph xGT graph analytics engine.
Author-email: Rocketgraph <support@rocketgraph.com>
License-Expression: Apache-2.0
Project-URL: Homepage, https://www.rocketgraph.com/
Project-URL: Documentation, https://docs.rocketgraph.com/user_ref/api/index.html
Project-URL: Changelog, https://docs.rocketgraph.com/launch_notes/index.html
Keywords: Rocketgraph,xGT,graph,cypher
Classifier: Development Status :: 5 - Production/Stable
Classifier: Operating System :: POSIX
Classifier: Operating System :: Unix
Classifier: Programming Language :: Python :: 3
Classifier: Programming Language :: Python :: 3.9
Classifier: Programming Language :: Python :: 3.10
Classifier: Programming Language :: Python :: 3.11
Classifier: Programming Language :: Python :: 3.12
Classifier: Programming Language :: Python :: 3.13
Classifier: Topic :: Database
Classifier: Topic :: Database :: Front-Ends
Requires-Python: <3.14,>=3.9
License-File: LICENSE.txt
Requires-Dist: grpcio>=1.73.1
Requires-Dist: isodate>=0.6.1
Requires-Dist: protobuf>=6
Requires-Dist: pyarrow>=20.0.0
Provides-Extra: extra
Requires-Dist: pandas>=0.24.2; extra == "extra"
Requires-Dist: jupyter; extra == "extra"
Dynamic: license-file
